kubectl_splunk/__init__.py
kubectl_splunk/main.py
tests/__init__.py
tests/test_kubectl_splunk.py
kubectl_splunk-1.6.dist-info/METADATA
kubectl_splunk-1.6.dist-info/WHEEL
kubectl_splunk-1.6.dist-info/entry_points.txt
kubectl_splunk-1.6.dist-info/top_level.txt
kubectl_splunk-1.6.dist-info/RECORD
