Metadata-Version: 2.1
Name: kubectl-splunk
Version: 1.6
Summary: A kubectl plugin to manage Splunk instances within Kubernetes pods.
Home-page: https://github.com/splunk/splunk-operator/tools/kubectl-splunk
Author: Splunk
Author-email: support@splunk.com
Classifier: Programming Language :: Python :: 3
Classifier: Operating System :: OS Independent
Requires-Python: >=3.6
Requires-Dist: requests
Requires-Dist: argcomplete
